{"is_source_file": true, "format": "JavaScript (React JSX)", "description": "This source file defines a React component for a calculator frontend, including UI controls, keyboard support, and interaction logic.", "external_files": ["./lib/calcEngine", "./App.module.css"], "external_methods": ["evaluateExpression", "formatResult", "sanitizeInputSequence"], "published": ["App"], "classes": [], "methods": [{"name": "App()", "description": "Main React component implementing the calculator UI with keyboard support and display logic.", "scope": "", "scopeKind": ""}], "calls": ["evaluateExpression", "formatResult", "sanitizeInputSequence"], "search-terms": ["React", "calcEngine", "calculator UI", "keyboard support", "App component", "calculator display", "CSS modules"], "state": 2, "file_id": 8, "knowledge_revision": 30, "git_revision": "a6d783eb021ee010da857d97d7f9e4ee25c52987", "revision_history": [{"25": "a6d783eb021ee010da857d97d7f9e4ee25c52987"}, {"30": "a6d783eb021ee010da857d97d7f9e4ee25c52987"}], "ctags": [{"_type": "tag", "name": "App", "path": "/home/kavia/workspace/code-generation/basic-calculator-172707-172716/calculator_frontend/src/App.js", "pattern": "/^function App() {$/", "language": "JavaScript", "kind": "function", "signature": "()"}, {"_type": "tag", "name": "display", "path": "/home/kavia/workspace/code-generation/basic-calculator-172707-172716/calculator_frontend/src/App.js", "pattern": "/^            value={display || (lastResult !== null ? String(lastResult) : '')}$/", "language": "JavaScript", "kind": "field", "scope": "App.value", "scopeKind": "class"}, {"_type": "tag", "name": "styles", "path": "/home/kavia/workspace/code-generation/basic-calculator-172707-172716/calculator_frontend/src/App.js", "pattern": "/^            className={styles.display}$/", "language": "JavaScript", "kind": "field", "scope": "App.className", "scopeKind": "class"}, {"_type": "tag", "name": "styles", "path": "/home/kavia/workspace/code-generation/basic-calculator-172707-172716/calculator_frontend/src/App.js", "pattern": "/^    <div className={styles.wrapper} ref={containerRef}>$/", "language": "JavaScript", "kind": "field", "scope": "App.AnonymousClassa4a79f950101", "scopeKind": "class"}], "hash": "74a2684434d472350f4c3ba3e79a181b", "format-version": 4, "code-base-name": "calculator_frontend", "filename": "calculator_frontend/src/App.js", "fields": [{"name": "value={display || (lastResult !== null ? String(lastResult) : '')}", "scope": "App.value", "scopeKind": "class", "description": "unavailable"}, {"name": "className={styles.display}", "scope": "App.className", "scopeKind": "class", "description": "unavailable"}, {"name": "<div className={styles.wrapper} ref={containerRef}>", "scope": "App.AnonymousClassa4a79f950101", "scopeKind": "class", "description": "unavailable"}]}